reru/__init__.py
reru/__init__.pyi
reru/py.typed
reru/reru.cpython-313-aarch64-linux-gnu.so
reru-0.1.2.dist-info/METADATA
reru-0.1.2.dist-info/WHEEL
reru-0.1.2.dist-info/licenses/LICENSE
reru-0.1.2.dist-info/RECORD
