Metadata-Version: 2.4
Name: reru
Version: 0.1.2
Classifier: Development Status :: 3 - Alpha
Classifier: Programming Language :: Rust
Classifier: Programming Language :: Python :: Implementation :: CPython
Classifier: Programming Language :: Python :: Implementation :: PyPy
Classifier: Programming Language :: Python :: 3
Classifier: Programming Language :: Python :: 3 :: Only
Classifier: Programming Language :: Python :: 3.9
Classifier: Programming Language :: Python :: 3.10
Classifier: Programming Language :: Python :: 3.11
Classifier: Programming Language :: Python :: 3.12
Classifier: Programming Language :: Python :: 3.13
Classifier: Programming Language :: Python :: 3.14
Classifier: Intended Audience :: Developers
Classifier: Topic :: Software Development :: Libraries :: Python Modules
Classifier: Topic :: Text Processing :: General
License-File: LICENSE
Summary: A high-performance, drop-in replacement for Python's re module, powered by Rust.
Keywords: regex,rust,performance,re,fast-re,pyo3
Author-email: "João Pedro Miranda C. Hluchan" <berrytern@gmail.com>
Maintainer-email: "João Pedro Miranda C. Hluchan" <berrytern@gmail.com>
License-Expression: Apache-2.0
Requires-Python: >=3.9
